re_order_imgs/__init__.py
re_order_imgs/cli.py
re_order_imgs/re_order_imgs.py
re_order_imgs/reorder_images_class.py
re_order_imgs-0.1.1.dist-info/AUTHORS.rst
re_order_imgs-0.1.1.dist-info/LICENSE
re_order_imgs-0.1.1.dist-info/METADATA
re_order_imgs-0.1.1.dist-info/WHEEL
re_order_imgs-0.1.1.dist-info/entry_points.txt
re_order_imgs-0.1.1.dist-info/top_level.txt
re_order_imgs-0.1.1.dist-info/RECORD
