Metadata-Version: 2.1
Name: re-order-imgs
Version: 0.1.1
Summary: A py package for reordering images
Home-page: https://github.com/M-Farag/re_order_imgs
Author: Mena Amin
Author-email: info@synth9.com
License: MIT license
Keywords: re_order_imgs
Classifier: Development Status :: 2 - Pre-Alpha
Classifier: Intended Audience :: Developers
Classifier: License :: OSI Approved :: MIT License
Classifier: Natural Language :: English
Classifier: Programming Language :: Python :: 3
Classifier: Programming Language :: Python :: 3.6
Classifier: Programming Language :: Python :: 3.7
Classifier: Programming Language :: Python :: 3.8
Requires-Python: >=3.6
License-File: LICENSE
License-File: AUTHORS.rst
Requires-Dist: Click >=7.0
Requires-Dist: exifread
Requires-Dist: Pillow
